setup.py
rdto_probability/Binomialdistribution_challenge.py
rdto_probability/Gaussiandistribution.py
rdto_probability/Generaldistribution.py
rdto_probability/__init__.py
rdto_probability.egg-info/PKG-INFO
rdto_probability.egg-info/SOURCES.txt
rdto_probability.egg-info/dependency_links.txt
rdto_probability.egg-info/not-zip-safe
rdto_probability.egg-info/top_level.txt