Metadata-Version: 2.1
Name: rdto-probability
Version: 0.1
Summary: Gaussian rdto_probability
Home-page: UNKNOWN
Author: Reuven Duer
Author-email: ruvduer@gmail.com
License: UNKNOWN
Platform: UNKNOWN
